pchjlib/__init__.py
pchjlib/caesar_cipher.py
pchjlib/desktop.ini
pchjlib/divisors_multiples.py
pchjlib/fibonacci.py
pchjlib/inversion_counting.py
pchjlib/logo.ico
pchjlib/pchjicon.py
pchjlib/pchjmain.py
pchjlib/prime_factorization.py
pchjlib/primes.py
pchjlib/sequence_generation.py
pchjlib/special_calculations.py
pchjlib/special_numbers1.py
pchjlib/special_numbers2.py
pchjlib/string_processing.py
pchjlib/twin_abundant.py
pchjlib/utils.py
pchjlib-1.7.2.dist-info/licenses/LICENSE.txt
pchjlib-1.7.2.dist-info/METADATA
pchjlib-1.7.2.dist-info/WHEEL
pchjlib-1.7.2.dist-info/entry_points.txt
pchjlib-1.7.2.dist-info/top_level.txt
pchjlib-1.7.2.dist-info/RECORD
