Metadata-Version: 2.4
Name: pchjlib
Version: 1.7.2
Summary: A Python toolkit for mathematical operations and string processing, including prime numbers, Fibonacci sequences, and Caesar ciphers.
Author: Joesifer
Project-URL: Homepage, https://github.com/Joesifer/pchjlib
Keywords: pchjlib,math,education,numbers,prime numbers,fibonacci,string processing,caesar cipher
Classifier: Development Status :: 5 - Production/Stable
Classifier: Intended Audience :: Developers
Classifier: Programming Language :: Python :: 3 :: Only
Classifier: Operating System :: OS Independent
Classifier: Topic :: Scientific/Engineering :: Mathematics
Classifier: Topic :: Software Development :: Libraries :: Python Modules
Requires-Python: >=3.7
License-File: LICENSE.txt
Provides-Extra: gmpy2
Requires-Dist: gmpy2>=2.1.5; extra == "gmpy2"
Provides-Extra: tests
Requires-Dist: unittest; extra == "tests"
Dynamic: license-file
